.gitignore
LICENSE
README.md
VAPr Quick-Start Guide.ipynb
pipeline.png
requirements.txt
sample_variant_document
setup.py
simpler.jpg
VAPr/__init__.py
VAPr/annovar_output_parsing.py
VAPr/annovar_running.py
VAPr/chunk_processing.py
VAPr/filtering.py
VAPr/validation.py
VAPr/vapr_core.py
VAPr/vcf_genotype_fields_parsing.py
VAPr/vcf_merging.py
VAPr.egg-info/PKG-INFO
VAPr.egg-info/SOURCES.txt
VAPr.egg-info/dependency_links.txt
VAPr.egg-info/not-zip-safe
VAPr.egg-info/requires.txt
VAPr.egg-info/top_level.txt
VAPr/tests/__init__.py
VAPr/tests/test_annovar_output_parsing.py
VAPr/tests/test_annovar_running.py
VAPr/tests/test_chunk_processing.py
VAPr/tests/test_filtering.py
VAPr/tests/test_validation.py
VAPr/tests/test_vapr_core.py
VAPr/tests/test_vcf_genotype_fields_parsing.py
VAPr/tests/test_vcf_merging.py
VAPr/tests/test_files/design_file_G1000_files.csv
VAPr/tests/test_files/design_file_by_dir_name.csv
VAPr/tests/test_files/annovar_dir/annotate_variation.pl
VAPr/tests/test_files/annovar_dir/coding_change.pl
VAPr/tests/test_files/annovar_dir/convert2annovar.pl
VAPr/tests/test_files/annovar_dir/retrieve_seq_from_fasta.pl
VAPr/tests/test_files/annovar_dir/table_annovar.pl
VAPr/tests/test_files/annovar_dir/variants_reduction.pl
VAPr/tests/test_files/fwriter_output/annotated_csv_RAND1_all_vars.csv
VAPr/tests/test_files/fwriter_output/annotated_csv_RAND_all_vars.csv
VAPr/tests/test_files/fwriter_output/annotated_csv_rand.csv
VAPr/tests/test_files/fwriter_output/annotated_csv_rand1.csv
VAPr/tests/test_files/test_input_dir/C90/C90.raw.Y.vcf.gz.tbi
VAPr/tests/test_files/test_input_dir/G1000/HG00096.vcf.gz
VAPr/tests/test_files/test_input_dir/G1000/HG00096.vcf.gz.tbi
VAPr/tests/test_files/test_input_dir/G1000/HG00097.vcf.gz
VAPr/tests/test_files/test_input_dir/G1000/HG00097.vcf.gz.tbi
VAPr/tests/test_files/test_input_dir/X45/X45.raw.22.vcf.gz.tbi
VAPr/tests/test_files/test_input_dir/X45/X45.raw.Y.vcf.gz.tbi
VAPr/tests/test_files/test_input_dir/X7/X7.raw.22.vcf--
VAPr/tests/test_files/test_input_dir/X7/X7.raw.22.vcf.gz.tbi
VAPr/tests/test_files/test_input_dir/X7/X7.raw.X.vcf.gz.tbi
dist/VAPr-0.1.tar.gz
dist/VAPr-0.2.tar.gz
dist/VAPr-1.0.1.tar.gz
