Metadata-Version: 1.0
Name: VAPr
Version: 3.0
Summary: Package for NoSQL variant data storage, annotation and prioritization.
Home-page: https://github.com/ucsd-ccbb/VAPr
Author: Carlo Mazzaferro, Amanda Birmingham, Adam Mark
Author-email: cmazzafe@ucsd.edu
License: MIT
Platform: UNKNOWN
